autogs/__init__.py
autogs-0.0.0.dist-info/METADATA
autogs-0.0.0.dist-info/WHEEL
autogs-0.0.0.dist-info/top_level.txt
autogs-0.0.0.dist-info/RECORD
